src/verilog/behaviorial.v
/********************************************
Behaviorial modelling of air traffic control system.

Airport description:
1)Airport contains two runways perpendicular to each other
2)Runway B faces E-W direction and Runway A faces N-S

Group Number:21

Member 1:
Name:Archit Pandey
Roll:16CO153

Member 2:
Name:Mohit Bhasi
ROll:16CO126
*********************************************/


module runway_select(d,A,B,clk,en,signal);

/********************************************
Inputs :
1) d-signifies direction of travel bits
   00-East,10-West,01-South,11-North
2) Clock
3) Enable pin

Ouputs :
1) signal-signifies the output generated by
   the curcuit

Other Variables:
1) a-signifies the current state of runway a
2) b-signifies the current state of runway 
3) counta-counter for runway a, counts till 15
   and clears the runway after that
4) countb-counter for runway b, counts till 15
   and clears the runway after that
********************************************/
	input [1:0] d;
	input A,B;
	input clk;
	input en;
	output reg [3:0]signal;
	reg a = 1'b0;
	reg b = 1'b0;
	integer counta = 0;
	integer countb = 0;

//The en signal is used to represent that an input has been given to the circuit. It is negative edge triggererd, 
//any change in the value signifies a new input and hence a new set of computations is carried out.

	always@(negedge en)
	begin
		if(d == 2'b00)				//Plane is heading in E-W Direction
			if(b == 0)				//Runway B is free
			begin
				signal = 4'b1011;	//Land on Runway B
				b = 1'b1;			//Make Runway B occupied for next set of inputs
			end
			else if(a == 0)			//Runway A is free
			begin
				signal = 4'b1010;	//Land on Runway A
				a = 1'b1;			//Make Runway A occupied for next set of inputs
			end
			else
				signal = 4'b1101;	//If none of the runways are available send the wait signal
		if(d == 2'b01)				//Plane is heading in W-E Direction
            if(a == 0)				//Runway A is free
			begin
                signal = 4'b1010;	//Land on Runway A
				a = 1'b1;			//Make Runway A occupied for next set of inputs
			end
            else if(b == 0)			//Runway B is free
			begin
                signal = 4'b1011;	//Land on Runway B
				b = 1'b1;			//Make Runway B occupied for next set of inputs
			end
            else
                signal = 4'b1101;	//If none of the runways are available send the wait signal
		if(d == 2'b10)				//Plane is heading in N-S Direction
            if(b == 0)				//Runway B is free
			begin
                signal = 4'b1011;	//Land on Runway B
				b = 1'b1;			//Make Runway B occupied for next set of inputs
			end
            else if(a == 0)			//Runway A is free
			begin
                signal = 4'b1010;	//Land on Runway A
				a = 1'b1;			//Make Runway A occupied for next set of inputs
			end
            else
                signal = 4'b1101;	//If none of the runways are available send the wait signal
		if(d == 2'b11)				//Plane is heading in S-N Direction
            if(a == 0)				//Runway A is free
			begin
                signal = 4'b1010;	//Land on Runway A
				a = 1'b1;			//Make Runway A occupied for next set of inputs
			end
            else if(b == 0)			//Runway B is free
			begin
                signal = 4'b1011;	//Land on Runway B
				b = 1'b1;			//Make Runway B occupied for next set of inputs
			end
            else
                signal = 4'b1101;	//If none of the runways are available send the wait signal
	end

//The below is an implementation of a counter that counts till 15, if a is occupied the timer for a starts likewise, if b is 
//occupied timer for b starts. The timers reset and the runways are made free once the count reaches 15.

	always@(posedge clk)
	begin
		if(a == 1)
            counta = counta + 1;
        if(b == 1)
            countb = countb + 1;
        if(counta == 15)
            a = 0;
        if(countb == 15)
            b = 0;
	end
endmodule

src/verilog/testbench.v
/********************************************
Testbench of air traffic control system.

Airport description:
1)Airport contains two runways perpendicular to each other
2)Runway B faces E-W direction and Runway A faces N-S

Group Number:21

Member 1:
Name:Archit Pandey
Roll:16CO153

Member 2:
Name:Mohit Bhasi
ROll:16CO126
*********************************************/

`timescale 1ns/10ps
module testbench;

/********************************************
Inputs :
1) d-signifies direction of travel bits
   00-East,10-West,01-South,11-North
2) Clock
3) Enable pin
4) A,B-they are feedback from the current circuit
   which prevents a plane from landing on an 
   already occupied runway

Ouputs :
1) signal-signifies the output generated by
   the curcuit

Other Variables:
1) a-signifies the current state of runway a
2) b-signifies the current state of runway 
3) counta-counter for runway a, counts till 15
   and clears the runway after that
4) countb-counter for runway b, counts till 15
   and clears the runway after that
********************************************/
    reg en;
    reg clk;
    reg [1:0] d;
    wire [3:0]signal;
    runway_select runway_pick(d,A,B,clk,en,signal);             //Create an object of type runway_select
    initial 
    begin        
        clk = 1'b0;
        repeat (100)
        #10 clk = ~clk;                                     //Create clock 
    end 
    initial
    begin
        $dumpfile("behavioural.vcd");                            //Create the vcd file
        $dumpvars(0,runway_pick);                           

//Uniform direction is maintained throught the test cases, but the frequency of inputs vary and 
//hence each time assigned runway may not be in direction of travel. As each operation of landing takes 15 seconds, 
//the outputs stay for consecutive inputs. For example : if runway A and B are full and a new plane wants to land,
//the circuit will sendout the wait signal for the next 15 seconds regardless of the number of times the circuit receives an input
// until a runway becomes free

        en = 1'b1;                                          //Enable switch is turned on to make the circuit take input
        d = 2'b00;
        #10
        en = 1'b0;                                          //Disabling the switch signifies input has been succesfully given
        $monitor("Direction: %d Signal: %d", d, signal);    //Display

        #100
        en = 1'b1;                                          //Enable switch is turned on to make the circuit take input
        d = 2'b00;
        #10
        en = 1'b0;                                          //Disabling the switch signifies input has been succesfully given
        $monitor("Direction: %d Signal: %d", d, signal);    //Display

        #100
        en = 1'b1;                                          //Enable switch is turned on to make the circuit take input
        d = 2'b00;
        #10
        en = 1'b0;                                          //Disabling the switch signifies input has been succesfully given
        $monitor("Direction: %d Signal: %d", d, signal);    //Display

//At this point all the runways are full for the next 15 seconds and the frequency of input is increased
//to show that the circuit will output the wait signal for the next 15 seconds

        #20
        en = 1'b1;                                          //Enable switch is turned on to make the circuit take input
        d = 2'b00;
        #10
        en = 1'b0;                                          //Disabling the switch signifies input has been succesfully given
        $monitor("Direction: %d Signal: %d", d, signal);    //Display

        #20
        en = 1'b1;                                          //Enable switch is turned on to make the circuit take input
        d = 2'b00;
        #10   
        en = 1'b0;                                          //Disabling the switch signifies input has been succesfully given              
        $monitor("Direction: %d Signal: %d", d, signal);    //Display

        #20
        en = 1'b1;                                          //Enable switch is turned on to make the circuit take input
        d = 2'b00;
        #10
        en = 1'b0;                                          //Disabling the switch signifies input has been succesfully given
        $monitor("Direction: %d Signal: %d", d, signal);    //Display
        
    end
endmodule

src/verilog/behavioural.vcd
$date
	Tue Nov  7 14:24:43 2017
$end
$version
	Icarus Verilog
$end
$timescale
	10ps
$end
$scope module testbench $end
$scope module runway_pick $end
$var wire 1 ! A $end
$var wire 1 " B $end
$var wire 1 # clk $end
$var wire 2 $ d [1:0] $end
$var wire 1 % en $end
$var reg 1 & a $end
$var reg 1 ' b $end
$var reg 4 ( signal [3:0] $end
$var integer 32 ) counta [31:0] $end
$var integer 32 * countb [31:0] $end
$upscope $end
$upscope $end
$enddefinitions $end
#0
$dumpvars
b0 *
b0 )
bx (
0'
0&
1%
b0 $
0#
z"
z!
$end
#1000
1'
b1011 (
0%
1#
#2000
0#
#3000
b1 *
1#
#4000
0#
#5000
b10 *
1#
#6000
0#
#7000
b11 *
1#
#8000
0#
#9000
b100 *
1#
#10000
0#
#11000
b101 *
1#
1%
#12000
1&
b1010 (
0#
0%
#13000
b110 *
b1 )
1#
#14000
0#
#15000
b111 *
b10 )
1#
#16000
0#
#17000
b1000 *
b11 )
1#
#18000
0#
#19000
b1001 *
b100 )
1#
#20000
0#
#21000
b1010 *
b101 )
1#
#22000
0#
1%
#23000
b1011 *
b110 )
b1101 (
1#
0%
#24000
0#
#25000
b1100 *
b111 )
1#
1%
#26000
0#
0%
#27000
b1101 *
b1000 )
1#
#28000
0#
1%
#29000
b1110 *
b1001 )
1#
0%
#30000
0#
#31000
0'
b1111 *
b1010 )
1#
1%
#32000
1'
b1011 (
0#
0%
#33000
b10000 *
b1011 )
1#
#34000
0#
#35000
b10001 *
b1100 )
1#
#36000
0#
#37000
b10010 *
b1101 )
1#
#38000
0#
#39000
b10011 *
b1110 )
1#
#40000
0#
#41000
0&
b10100 *
b1111 )
1#
#42000
0#
#43000
b10101 *
1#
#44000
0#
#45000
b10110 *
1#
#46000
0#
#47000
b10111 *
1#
#48000
0#
#49000
b11000 *
1#
#50000
0#
#51000
b11001 *
1#
#52000
0#
#53000
b11010 *
1#
#54000
0#
#55000
b11011 *
1#
#56000
0#
#57000
b11100 *
1#
#58000
0#
#59000
b11101 *
1#
#60000
0#
#61000
b11110 *
1#
#62000
0#
#63000
b11111 *
1#
#64000
0#
#65000
b100000 *
1#
#66000
0#
#67000
b100001 *
1#
#68000
0#
#69000
b100010 *
1#
#70000
0#
#71000
b100011 *
1#
#72000
0#
#73000
b100100 *
1#
#74000
0#
#75000
b100101 *
1#
#76000
0#
#77000
b100110 *
1#
#78000
0#
#79000
b100111 *
1#
#80000
0#
#81000
b101000 *
1#
#82000
0#
#83000
b101001 *
1#
#84000
0#
#85000
b101010 *
1#
#86000
0#
#87000
b101011 *
1#
#88000
0#
#89000
b101100 *
1#
#90000
0#
#91000
b101101 *
1#
#92000
0#
#93000
b101110 *
1#
#94000
0#
#95000
b101111 *
1#
#96000
0#
#97000
b110000 *
1#
#98000
0#
#99000
b110001 *
1#
