src/verilog/VerilogDM-126-153.v
/********************************************
Dataflow modelling of air traffic control system.

Airport description:
1)Airport contains two runways perpendicular to each other
2)Runway B faces E-W direction and Runway A faces N-S

Group Number:21

Member 1:
Name:Archit Pandey
Roll:16CO153

Member 2:
Name:Mohit Bhasi
ROll:16CO126
*********************************************/

module VerilogDM_126_153(d,A,B,clk,E,signal);

/********************************************
Inputs :
1) d-signifies direction of travel bits
   00-East,10-West,01-South,11-North
2) Clock
3) Enable pin
4) A,B-they are feedback from the current circuit
   which prevents a plane from landing on an 
   already occupied runway

Ouputs :
1) signal-signifies the output generated by
   the curcuit

Other Variables:
1) a-signifies the current state of runway a
2) b-signifies the current state of runway 
3) counta-counter for runway a, counts till 15
   and clears the runway after that
4) countb-counter for runway b, counts till 15
   and clears the runway after that
********************************************/
	reg a;
	reg b;
	integer counta = 0;
	integer countb = 0;
	input [1:0]d;
	input E,clk;	
	output reg [3:0]signal;
	output reg A,B;
	always@(negedge E)
	begin

		assign a=A; 											//feedback received from previous function call used
		assign b=B;												//to compute current runway status

//Below is a boolean function that generates a 4 bit output representing the runway to land on
//1010 signifies land on a, 1011 signifies land on b, 1101 signifies wait

		assign signal[3]=1;
		assign signal[2]=a&b;
		assign signal[1]=~signal[2];
		assign signal[0]=a|(~b&~d[1]);
	end
	always@(posedge clk)
	begin
		assign countb=(signal==4'b1011)?countb+1:countb+1;		//If current landing is on B, start timer  for B
		assign B=(countb>5)?1:0;								//Hold runway B full till landing takes place
		assign countb=(countb==15)?0:countb;					//Reset counter for runway b when it reaches 15

	end	
	always@(posedge clk)
	begin
		assign counta=(signal==4'b1010)?counta+1:counta+1;		//If current landing is on A, start timer  for A
		assign A=(counta<10)?1:0;								//Hold runway A full till landing takes place
		assign counta=(counta==15)?0:counta;					//Reset counter for runway b when it reaches 15

	end
endmodule

src/verilog/Verilog_126_153.v
/********************************************
Testbench of air traffic control system.

Airport description:
1)Airport contains two runways perpendicular to each other
2)Runway B faces E-W direction and Runway A faces N-S

Group Number:21

Member 1:
Name:Archit Pandey
Roll:16CO153

Member 2:
Name:Mohit Bhasi
ROll:16CO126
*********************************************/

`timescale 1ns/10ps
module testbench;

/********************************************
Inputs :
1) d-signifies direction of travel bits
   00-East,10-West,01-South,11-North
2) Clock
3) Enable pin
4) A,B-they are feedback from the current circuit
   which prevents a plane from landing on an 
   already occupied runway

Ouputs :
1) signal-signifies the output generated by
   the curcuit

Other Variables:
1) a-signifies the current state of runway a
2) b-signifies the current state of runway 
3) counta-counter for runway a, counts till 15
   and clears the runway after that
4) countb-counter for runway b, counts till 15
   and clears the runway after that
********************************************/
    reg en;
    reg clk;
    reg [1:0] d;
    wire [3:0]signal;
    VerilogDM_126_153 runway_pick(d,A,B,clk,en,signal);             //Create an object of type runway_select
    //VerilogBM_126_153 runway_pick(d,A,B,clk,en,signal);             //Create an object of type runway_select
    initial 
    begin        
        clk = 1'b0;
        repeat (60)
        #10 clk = ~clk;                                     //Create clock 
    end 
    initial
    begin
        $dumpfile("dataflow.vcd");                            //Create the vcd file
	//$dumpfile("behavioral.vcd");			      //Create the vcd file
        $dumpvars(0,runway_pick);                           

//Uniform direction is maintained throught the test cases, but the frequency of inputs vary and 
//hence each time assigned runway may not be in direction of travel. As each operation of landing takes 15 seconds, 
//the outputs stay for consecutive inputs. For example : if runway A and B are full and a new plane wants to land,
//the circuit will sendout the wait signal for the next 15 seconds regardless of the number of times the circuit receives an input
// until a runway becomes free

        en = 1'b1;                                          //Enable switch is turned on to make the circuit take input
        d = 2'b00;
        #10
        en = 1'b0;                                          //Disabling the switch signifies input has been succesfully given
        $monitor("Direction: %d Signal: %d", d, signal);    //Display

        #100
        en = 1'b1;                                          //Enable switch is turned on to make the circuit take input
        d = 2'b00;
        #10
        en = 1'b0;                                          //Disabling the switch signifies input has been succesfully given
        $monitor("Direction: %d Signal: %d", d, signal);    //Display

        #100
        en = 1'b1;                                          //Enable switch is turned on to make the circuit take input
        d = 2'b00;
        #10
        en = 1'b0;                                          //Disabling the switch signifies input has been succesfully given
        $monitor("Direction: %d Signal: %d", d, signal);    //Display

//At this point all the runways are full for the next 15 seconds and the frequency of input is increased
//to show that the circuit will output the wait signal for the next 15 seconds

        #20
        en = 1'b1;                                          //Enable switch is turned on to make the circuit take input
        d = 2'b00;
        #10
        en = 1'b0;                                          //Disabling the switch signifies input has been succesfully given
        $monitor("Direction: %d Signal: %d", d, signal);    //Display

        #20
        en = 1'b1;                                          //Enable switch is turned on to make the circuit take input
        d = 2'b00;
        #10   
        en = 1'b0;                                          //Disabling the switch signifies input has been succesfully given              
        $monitor("Direction: %d Signal: %d", d, signal);    //Display

        #20
        en = 1'b1;                                          //Enable switch is turned on to make the circuit take input
        d = 2'b00;
        #10
        en = 1'b0;                                          //Disabling the switch signifies input has been succesfully given
        $monitor("Direction: %d Signal: %d", d, signal);    //Display
        
    end
endmodule

src/verilog/VerilogDM-126-153.vcd
$date
	Tue Nov  7 21:55:25 2017
$end
$version
	Icarus Verilog
$end
$timescale
	10ps
$end
$scope module testbench $end
$scope module runway_pick $end
$var wire 1 ! E $end
$var wire 1 " clk $end
$var wire 2 # d [1:0] $end
$var reg 1 $ A $end
$var reg 1 % B $end
$var reg 1 & a $end
$var reg 1 ' b $end
$var integer 32 ( counta [31:0] $end
$var integer 32 ) countb [31:0] $end
$var reg 4 * signal [3:0] $end
$upscope $end
$upscope $end
$enddefinitions $end
#0
$dumpvars
bx *
b0 )
b0 (
x'
x&
x%
x$
b0 #
0"
1!
$end
#1000
b1011 *
0'
1&
0%
b1 )
1$
b1 (
0!
1"
#2000
0"
#3000
1$
1&
b10 (
0%
0'
b10 )
1"
#4000
0"
#5000
0%
0'
b11 )
1$
1&
b11 (
1"
#6000
0"
#7000
1$
1&
b100 (
0%
0'
b100 )
1"
#8000
0"
#9000
0%
0'
b101 )
1$
1&
b101 (
1"
#10000
0"
#11000
1$
1&
b110 (
1%
1'
b110 )
1"
1!
#12000
b1101 *
1'
1&
0"
0!
#13000
1%
1'
b111 )
1$
1&
b111 (
1"
#14000
0"
#15000
1$
1&
b1000 (
1%
1'
b1000 )
1"
#16000
0"
#17000
1%
1'
b1001 )
1$
1&
b1001 (
1"
#18000
0"
#19000
0$
0&
b1010 (
1%
1'
b1010 )
1"
#20000
0"
#21000
1%
1'
b1011 )
0$
0&
b1011 (
1"
#22000
0"
1!
#23000
0$
b1100 (
1%
b1100 )
b1010 *
1'
0&
1"
0!
#24000
0"
#25000
1%
1'
b1101 )
0$
0&
b1101 (
1"
1!
#26000
b1010 *
1'
0&
0"
0!
#27000
0$
0&
b1110 (
1%
1'
b1110 )
1"
#28000
0"
1!
#29000
1%
b0 )
0$
b0 (
b1010 *
1'
0&
1"
0!
#30000
0"
#31000
1$
1&
b1 (
0%
0'
b1 )
1"
1!
#32000
b1011 *
0'
1&
0"
0!
#33000
0%
0'
b10 )
1$
1&
b10 (
1"
#34000
0"
#35000
1$
1&
b11 (
0%
0'
b11 )
1"
#36000
0"
#37000
0%
0'
b100 )
1$
1&
b100 (
1"
#38000
0"
#39000
1$
1&
b101 (
0%
0'
b101 )
1"
#40000
0"
#41000
1%
1'
b110 )
1$
1&
b110 (
1"
#42000
0"
#43000
1$
1&
b111 (
1%
1'
b111 )
1"
#44000
0"
#45000
1%
1'
b1000 )
1$
1&
b1000 (
1"
#46000
0"
#47000
1$
1&
b1001 (
1%
1'
b1001 )
1"
#48000
0"
#49000
1%
1'
b1010 )
0$
0&
b1010 (
1"
#50000
0"
#51000
0$
0&
b1011 (
1%
1'
b1011 )
1"
#52000
0"
#53000
1%
1'
b1100 )
0$
0&
b1100 (
1"
#54000
0"
#55000
0$
0&
b1101 (
1%
1'
b1101 )
1"
#56000
0"
#57000
1%
1'
b1110 )
0$
0&
b1110 (
1"
#58000
0"
#59000
0$
0&
b0 (
1%
1'
b0 )
1"
