src/verilog/dataflow/runway_picker.v
module runway_picker(d,A,B,clk,E,signal);
	reg a ,b;
	integer counta = 0, countb = 0;
	input [1:0]d;
	input E,clk;	
	output reg [3:0]signal;
	output reg A,B;
	always@(negedge E)
	begin
		assign a=A;
		assign b=B;
		assign signal[3]=1;
		assign signal[2]=a&b;
		assign signal[1]=~signal[2];
		assign signal[0]=a|(~b&~d[1]);
	end
	always@(posedge clk or b)
	begin
		assign countb=(signal==4'b1011)?countb+1:countb+1;
		assign B=(countb>2)?1:0;
		assign countb=(countb==15)?0:countb;

	end	
	always@(posedge clk or a)
	begin
		assign counta=(signal==4'b1010)?counta+1:counta+1;
		assign A=(counta<15)?1:0;
		assign counta=(counta==15)?0:counta;

	end
	

endmodule

src/verilog/dataflow/testbench.v
`timescale 1ns/10ps
module tb_picker;
    reg en,clk;
    reg [1:0] d;
    wire [3:0]signal;
    wire A,B;
    runway_picker runway_pick(d,A,B,clk,en,signal);
    initial begin
        
        clk = 1'b0;
        repeat (100)
                #10 clk = ~clk;
    end 
    initial
    begin
        $dumpfile("output.vcd");
        $dumpvars(0,runway_pick);

                en = 1'b1;
                d = 2'b00;
        #10     en = 1'b0;
            //A=0;
           // B=0;
                $monitor("Direction: %d Signal: %d", d, signal);

        #100
                en = 1'b1;
                d = 2'b00;
        #10     en = 1'b0;
                $monitor("Direction: %d Signal: %d", d, signal);

        #100
                en = 1'b1;
                d = 2'b00;
        #10     en = 1'b0;
                $monitor("Direction: %d Signal: %d", d, signal);

        #20
                en = 1'b1;
                d = 2'b00;
        #10     en = 1'b0;
                $monitor("Direction: %d Signal: %d", d, signal);

        #20
                en = 1'b1;
                d = 2'b00;
        #10     en = 1'b0;
                $monitor("Direction: %d Signal: %d", d, signal);

        #20
                en = 1'b1;
                d = 2'b00;
        #10     en = 1'b0;
                $monitor("Direction: %d Signal: %d", d, signal);
        
    end
endmodule // tb

src/verilog/dataflow/output.vcd
$date
	Tue Nov  7 02:54:36 2017
$end
$version
	Icarus Verilog
$end
$timescale
	10ps
$end
$scope module tb_picker $end
$scope module runway_pick $end
$var wire 1 ! E $end
$var wire 1 " clk $end
$var wire 2 # d [1:0] $end
$var reg 1 $ A $end
$var reg 1 % B $end
$var reg 1 & a $end
$var reg 1 ' b $end
$var reg 4 ( signal [3:0] $end
$var integer 32 ) counta [31:0] $end
$var integer 32 * countb [31:0] $end
$upscope $end
$upscope $end
$enddefinitions $end
#0
$dumpvars
b0 *
b0 )
bx (
x'
x&
x%
x$
b0 #
0"
1!
$end
#1000
b1011 (
0'
1&
1$
b10 )
0%
b10 *
0!
1"
#2000
0"
#3000
b11 )
1'
1%
b11 *
1"
#4000
0"
#5000
b100 )
b100 *
1"
#6000
0"
#7000
b101 )
b101 *
1"
#8000
0"
#9000
b110 )
b110 *
1"
#10000
0"
#11000
b111 )
b111 *
1"
1!
#12000
b1101 (
0"
0!
#13000
b1000 )
b1000 *
1"
#14000
0"
#15000
b1001 )
b1001 *
1"
#16000
0"
#17000
b1010 )
b1010 *
1"
#18000
0"
#19000
b1011 )
b1011 *
1"
#20000
0"
#21000
b1100 )
b1100 *
1"
#22000
0"
1!
#23000
b1101 )
b1101 *
1"
0!
#24000
0"
#25000
b1110 )
b1110 *
1"
1!
#26000
0"
0!
#27000
0&
0$
b0 )
b0 *
1"
#28000
0"
1!
#29000
1&
1$
b1 )
0'
0%
b1 *
b1010 (
1"
0!
#30000
0"
#31000
b10 )
b10 *
1"
1!
#32000
b1011 (
0"
0!
#33000
b11 )
1'
1%
b11 *
1"
#34000
0"
#35000
b100 )
b100 *
1"
#36000
0"
#37000
b101 )
b101 *
1"
#38000
0"
#39000
b110 )
b110 *
1"
#40000
0"
#41000
b111 )
b111 *
1"
#42000
0"
#43000
b1000 )
b1000 *
1"
#44000
0"
#45000
b1001 )
b1001 *
1"
#46000
0"
#47000
b1010 )
b1010 *
1"
#48000
0"
#49000
b1011 )
b1011 *
1"
#50000
0"
#51000
b1100 )
b1100 *
1"
#52000
0"
#53000
b1101 )
b1101 *
1"
#54000
0"
#55000
b1110 )
b1110 *
1"
#56000
0"
#57000
0&
0$
b0 )
b0 *
1"
#58000
0"
#59000
1&
1$
b1 )
0'
0%
b1 *
1"
#60000
0"
#61000
b10 )
b10 *
1"
#62000
0"
#63000
b11 )
1'
1%
b11 *
1"
#64000
0"
#65000
b100 )
b100 *
1"
#66000
0"
#67000
b101 )
b101 *
1"
#68000
0"
#69000
b110 )
b110 *
1"
#70000
0"
#71000
b111 )
b111 *
1"
#72000
0"
#73000
b1000 )
b1000 *
1"
#74000
0"
#75000
b1001 )
b1001 *
1"
#76000
0"
#77000
b1010 )
b1010 *
1"
#78000
0"
#79000
b1011 )
b1011 *
1"
#80000
0"
#81000
b1100 )
b1100 *
1"
#82000
0"
#83000
b1101 )
b1101 *
1"
#84000
0"
#85000
b1110 )
b1110 *
1"
#86000
0"
#87000
0&
0$
b0 )
b0 *
1"
#88000
0"
#89000
1&
1$
b1 )
0'
0%
b1 *
1"
#90000
0"
#91000
b10 )
b10 *
1"
#92000
0"
#93000
b11 )
1'
1%
b11 *
1"
#94000
0"
#95000
b100 )
b100 *
1"
#96000
0"
#97000
b101 )
b101 *
1"
#98000
0"
#99000
b110 )
b110 *
1"
